mysqldbutils/__init__.py
mysqldbutils/main.py
mysqldbutils-0.6.dist-info/METADATA
mysqldbutils-0.6.dist-info/WHEEL
mysqldbutils-0.6.dist-info/top_level.txt
mysqldbutils-0.6.dist-info/RECORD
