Metadata-Version: 2.1
Name: mysqldbutils
Version: 0.6
Summary: UNKNOWN
Home-page: https://github.com/technicalheist/mysqldbutils.git
Author: Technical Heist
Author-email: contact@technicalheist.com
License: MIT
Keywords: MySQL,database,CRUD,utility
Platform: UNKNOWN
Classifier: Development Status :: 3 - Alpha
Classifier: Intended Audience :: Developers
Classifier: License :: OSI Approved :: MIT License
Classifier: Programming Language :: Python :: 3
Classifier: Programming Language :: Python :: 3.6
Classifier: Programming Language :: Python :: 3.7
Classifier: Programming Language :: Python :: 3.8
Classifier: Programming Language :: Python :: 3.9
Requires-Dist: mysql-connector-python
